dictdots
