Metadata-Version: 2.1
Name: DictDots
Version: 0.2.0
Summary: DictDots is a tool to access nested dictionaries without long if-else chains.
Home-page: https://github.com/alexlambson/python-dict-dots/
Author: Alex Lambson
Author-email: support@alexlambson.com
License: GPLv3
Platform: UNKNOWN
Classifier: License :: OSI Approved :: GNU General Public License v3 (GPLv3)
Classifier: Development Status :: 3 - Alpha
Classifier: Intended Audience :: Developers
Classifier: Natural Language :: English
Classifier: Programming Language :: Python :: 3
Classifier: Programming Language :: Python :: 3 :: Only
Classifier: Programming Language :: Python :: 3.7
Classifier: Programming Language :: Python :: 3.8
Classifier: Topic :: Utilities
